[
  {
    "children": [],
    "configurations": [],
    "contacts": [],
    "created": 1680539622,
    "description": "",
    "deviceConfiguration": [],
    "deviceRules": {
      "firmwareUpgrade": "inherit",
      "rcOnly": "inherit",
      "rrm": "inherit"
    },
    "devices": [],
    "id": "a9b05498-7ee4-4e04-8e7b-3c75f30c281c",
    "locations": [],
    "managementPolicies": [],
    "managementPolicy": "",
    "managementRoles": [],
    "maps": [],
    "modified": 1680539622,
    "name": "TestOrg",
    "notes": [],
    "parent": "0000-0000-0000",
    "sourceIP": [],
    "tags": [],
    "variables": [],
    "venues": [
      "463256a1-5719-4b69-b9ff-78a5dc0a30b6"
    ]
  },
  {
    "children": [],
    "configurations": [],
    "contacts": [],
    "created": 1672316893,
    "description": "",
    "deviceConfiguration": [],
    "deviceRules": {
      "firmwareUpgrade": "inherit",
      "rcOnly": "inherit",
      "rrm": "inherit"
    },
    "devices": [],
    "id": "4ab3fc5f-c672-474f-92a1-781c1d02fa1d",
    "locations": [],
    "managementPolicies": [],
    "managementPolicy": "",
    "managementRoles": [],
    "maps": [],
    "modified": 1672316893,
    "name": "New Org",
    "notes": [],
    "parent": "0000-0000-0000",
    "sourceIP": [],
    "tags": [],
    "variables": [],
    "venues": [
      "8ae68ede-096d-4341-8f22-974a61a79985",
      "a0abfb61-b1ec-4753-bbe4-618907f093bf"
    ]
  },
  {
    "children": [],
    "configurations": [],
    "contacts": [],
    "created": 1673593977,
    "description": "",
    "deviceConfiguration": [],
    "deviceRules": {
      "firmwareUpgrade": "inherit",
      "rcOnly": "inherit",
      "rrm": "inherit"
    },
    "devices": [],
    "id": "896ea3db-545e-4e8a-b0b2-eae2550c4ee7",
    "locations": [],
    "managementPolicies": [],
    "managementPolicy": "",
    "managementRoles": [],
    "maps": [],
    "modified": 1673593977,
    "name": "SravanAbhiramYerru",
    "notes": [],
    "parent": "0000-0000-0000",
    "sourceIP": [],
    "tags": [],
    "variables": [],
    "venues": [
      "b6d09cfc-8509-4da6-9963-41295f83bdb9"
    ]
  },
  {
    "children": [],
    "configurations": [],
    "contacts": [],
    "created": 1672341018,
    "description": "",
    "deviceConfiguration": [],
    "deviceRules": {
      "firmwareUpgrade": "inherit",
      "rcOnly": "inherit",
      "rrm": "inherit"
    },
    "devices": [],
    "id": "3457d9a0-47c9-4b1e-b3b8-9f8f83c414db",
    "locations": [],
    "managementPolicies": [],
    "managementPolicy": "",
    "managementRoles": [],
    "maps": [],
    "modified": 1672341018,
    "name": "FW_org",
    "notes": [],
    "parent": "0000-0000-0000",
    "sourceIP": [],
    "tags": [],
    "variables": [],
    "venues": [
      "0d36b711-31ef-4458-bd90-1997fde3420e"
    ]
  },
  {
    "children": [],
    "configurations": [],
    "contacts": [],
    "created": 1672321383,
    "description": "",
    "deviceConfiguration": [],
    "deviceRules": {
      "firmwareUpgrade": "inherit",
      "rcOnly": "inherit",
      "rrm": "inherit"
    },
    "devices": [],
    "id": "9fc08205-2a94-4d3f-b988-51041ad381b5",
    "locations": [],
    "managementPolicies": [],
    "managementPolicy": "",
    "managementRoles": [],
    "maps": [],
    "modified": 1672321383,
    "name": "Straw Hat",
    "notes": [],
    "parent": "0000-0000-0000",
    "sourceIP": [],
    "tags": [],
    "variables": [],
    "venues": [
      "936949b1-e8e1-40c2-a553-f7ca52591436"
    ]
  },
  {
    "children": [],
    "configurations": [],
    "contacts": [],
    "created": 1673245543,
    "description": "",
    "deviceConfiguration": [],
    "deviceRules": {
      "firmwareUpgrade": "inherit",
      "rcOnly": "inherit",
      "rrm": "inherit"
    },
    "devices": [],
    "id": "92894775-6e22-42a6-9257-abb4aa838690",
    "locations": [],
    "managementPolicies": [],
    "managementPolicy": "",
    "managementRoles": [],
    "maps": [],
    "modified": 1673339451,
    "name": "ORG_UPDATE123",
    "notes": [],
    "parent": "0000-0000-0000",
    "sourceIP": [],
    "tags": [],
    "variables": [],
    "venues": [
      "4d392552-c9a8-445d-ad81-970a2b69a0d9",
      "7c51abdc-81da-4ad0-b610-3e6e15b4253f"
    ]
  },
  {
    "children": [],
    "configurations": [],
    "contacts": [],
    "created": 1672374665,
    "description": "",
    "deviceConfiguration": [],
    "deviceRules": {
      "firmwareUpgrade": "inherit",
      "rcOnly": "inherit",
      "rrm": "inherit"
    },
    "devices": [],
    "id": "f4492fa6-fe55-4967-b0e6-31c266994d25",
    "locations": [],
    "managementPolicies": [],
    "managementPolicy": "",
    "managementRoles": [],
    "maps": [],
    "modified": 1672374665,
    "name": "FW Upgrade",
    "notes": [],
    "parent": "0000-0000-0000",
    "sourceIP": [],
    "tags": [],
    "variables": [],
    "venues": [
      "ab401d3d-d0b9-40b9-8e93-280a6b1eaf0c"
    ]
  },
  {
    "children": [],
    "configurations": [],
    "contacts": [],
    "created": 1672331243,
    "description": "",
    "deviceConfiguration": [],
    "deviceRules": {
      "firmwareUpgrade": "inherit",
      "rcOnly": "inherit",
      "rrm": "inherit"
    },
    "devices": [],
    "id": "f55540d0-29f1-4d9f-8106-f8fea7a736a8",
    "locations": [],
    "managementPolicies": [],
    "managementPolicy": "",
    "managementRoles": [],
    "maps": [],
    "modified": 1672331243,
    "name": "Org-1",
    "notes": [],
    "parent": "0000-0000-0000",
    "sourceIP": [],
    "tags": [],
    "variables": [],
    "venues": [
      "0fe38dc2-b734-4429-9a04-d4375b058a2f"
    ]
  },
  {
    "children": [],
    "configurations": [],
    "contacts": [],
    "created": 1672375445,
    "description": "",
    "deviceConfiguration": [],
    "deviceRules": {
      "firmwareUpgrade": "inherit",
      "rcOnly": "inherit",
      "rrm": "inherit"
    },
    "devices": [],
    "id": "87d84d67-482b-46e6-9d0e-58c1c49c79b8",
    "locations": [],
    "managementPolicies": [],
    "managementPolicy": "",
    "managementRoles": [],
    "maps": [],
    "modified": 1672375445,
    "name": "FW_UPGRADE_TEST",
    "notes": [],
    "parent": "0000-0000-0000",
    "sourceIP": [],
    "tags": [],
    "variables": [],
    "venues": [
      "a7a53b0a-4ef8-4860-a482-4dfd9a893cc7"
    ]
  },
  {
    "children": [],
    "configurations": [],
    "contacts": [],
    "created": 1672331994,
    "description": "",
    "deviceConfiguration": [],
    "deviceRules": {
      "firmwareUpgrade": "inherit",
      "rcOnly": "inherit",
      "rrm": "inherit"
    },
    "devices": [],
    "id": "d69afa82-d3a2-44ec-825b-7df86e6062c2",
    "locations": [],
    "managementPolicies": [],
    "managementPolicy": "",
    "managementRoles": [],
    "maps": [],
    "modified": 1672331994,
    "name": "Org-1",
    "notes": [],
    "parent": "0000-0000-0000",
    "sourceIP": [],
    "tags": [],
    "variables": [],
    "venues": [
      "1137418a-e565-4ae4-978d-326a3d9a4da1"
    ]
  },
  {
    "children": [],
    "configurations": [],
    "contacts": [],
    "created": 1672381317,
    "description": "",
    "deviceConfiguration": [],
    "deviceRules": {
      "firmwareUpgrade": "inherit",
      "rcOnly": "inherit",
      "rrm": "inherit"
    },
    "devices": [],
    "id": "bd0ec852-16fb-40f2-8df0-5d2f47e37d0d",
    "locations": [],
    "managementPolicies": [],
    "managementPolicy": "",
    "managementRoles": [],
    "maps": [],
    "modified": 1672381317,
    "name": "BugsVerification",
    "notes": [],
    "parent": "0000-0000-0000",
    "sourceIP": [],
    "tags": [],
    "variables": [],
    "venues": [
      "9119e0d7-df5f-4f82-9c14-e71d25b09ccd"
    ]
  },
  {
    "children": [],
    "configurations": [],
    "contacts": [],
    "created": 1673530470,
    "description": "",
    "deviceConfiguration": [],
    "deviceRules": {
      "firmwareUpgrade": "inherit",
      "rcOnly": "inherit",
      "rrm": "inherit"
    },
    "devices": [],
    "id": "41fd71f4-6f0a-4c7b-a013-2bd2774a021f",
    "locations": [],
    "managementPolicies": [],
    "managementPolicy": "",
    "managementRoles": [],
    "maps": [],
    "modified": 1673530470,
    "name": "Deep River",
    "notes": [],
    "parent": "0000-0000-0000",
    "sourceIP": [],
    "tags": [],
    "variables": [],
    "venues": [
      "3af5d600-7b11-460f-8b05-0b73bce10905"
    ]
  },
  {
    "children": [],
    "configurations": [],
    "contacts": [],
    "created": 1694703500,
    "description": "",
    "deviceConfiguration": [],
    "deviceRules": {
      "firmwareUpgrade": "inherit",
      "rcOnly": "inherit",
      "rrm": "inherit"
    },
    "devices": [],
    "id": "be5d0bf6-225e-4ba9-82d3-8b1a83592ff3",
    "locations": [],
    "managementPolicies": [],
    "managementPolicy": "",
    "managementRoles": [],
    "maps": [],
    "modified": 1694703500,
    "name": "testtest1",
    "notes": [],
    "parent": "0000-0000-0000",
    "sourceIP": [],
    "tags": [],
    "variables": [],
    "venues": [
      "4ba84db0-86f2-464d-9c99-c3eed2bf6e1c"
    ]
  },
  {
    "children": [],
    "configurations": [],
    "contacts": [],
    "created": 1672324938,
    "description": "",
    "deviceConfiguration": [],
    "deviceRules": {
      "firmwareUpgrade": "inherit",
      "rcOnly": "inherit",
      "rrm": "inherit"
    },
    "devices": [],
    "id": "99ed0063-9782-4bc6-ac42-4a236d7d0a21",
    "locations": [],
    "managementPolicies": [],
    "managementPolicy": "",
    "managementRoles": [],
    "maps": [],
    "modified": 1672368221,
    "name": "Straw Hat",
    "notes": [],
    "parent": "0000-0000-0000",
    "sourceIP": [],
    "tags": [],
    "variables": [],
    "venues": [
      "a09197af-44a6-4e2d-8256-8c8847a4c30d"
    ]
  },
  {
    "children": [],
    "configurations": [],
    "contacts": [],
    "created": 1684413507,
    "description": "",
    "deviceConfiguration": [],
    "deviceRules": {
      "firmwareUpgrade": "inherit",
      "rcOnly": "inherit",
      "rrm": "inherit"
    },
    "devices": [],
    "id": "2d0eb497-8088-4f21-946b-26f75a462b16",
    "locations": [],
    "managementPolicies": [],
    "managementPolicy": "",
    "managementRoles": [],
    "maps": [],
    "modified": 1685012669,
    "name": "noor mehal",
    "notes": [],
    "parent": "0000-0000-0000",
    "sourceIP": [],
    "tags": [],
    "variables": [],
    "venues": [
      "1e4dccec-fa75-47b0-9e27-c447d9d0b63c"
    ]
  },
  {
    "children": [],
    "configurations": [],
    "contacts": [],
    "created": 1673594001,
    "description": "",
    "deviceConfiguration": [],
    "deviceRules": {
      "firmwareUpgrade": "inherit",
      "rcOnly": "inherit",
      "rrm": "inherit"
    },
    "devices": [],
    "id": "24e099a7-a5b3-497b-8822-7d0587cf8f09",
    "locations": [],
    "managementPolicies": [],
    "managementPolicy": "",
    "managementRoles": [],
    "maps": [],
    "modified": 1673594001,
    "name": "SravanAbhiram_business",
    "notes": [],
    "parent": "0000-0000-0000",
    "sourceIP": [],
    "tags": [],
    "variables": [],
    "venues": [
      "cae233cd-5485-4bd1-b9e9-13000f08d0f0"
    ]
  },
  {
    "children": [],
    "configurations": [],
    "contacts": [],
    "created": 1674194954,
    "description": "",
    "deviceConfiguration": [],
    "deviceRules": {
      "firmwareUpgrade": "inherit",
      "rcOnly": "inherit",
      "rrm": "inherit"
    },
    "devices": [],
    "id": "9cd9d64d-88ae-45cc-8ba9-bb35c652777b",
    "locations": [],
    "managementPolicies": [],
    "managementPolicy": "",
    "managementRoles": [],
    "maps": [],
    "modified": 1674194954,
    "name": "ORG001",
    "notes": [],
    "parent": "0000-0000-0000",
    "sourceIP": [],
    "tags": [],
    "variables": [],
    "venues": [
      "05169d19-9214-4864-b0ad-0a31184d9e86"
    ]
  },
  {
    "children": [],
    "configurations": [],
    "contacts": [],
    "created": 1672385197,
    "description": "",
    "deviceConfiguration": [],
    "deviceRules": {
      "firmwareUpgrade": "inherit",
      "rcOnly": "inherit",
      "rrm": "inherit"
    },
    "devices": [],
    "id": "3cc621b4-3e10-420a-b3ef-781e5c694aef",
    "locations": [],
    "managementPolicies": [],
    "managementPolicy": "",
    "managementRoles": [],
    "maps": [],
    "modified": 1672385197,
    "name": "BugsVerification",
    "notes": [],
    "parent": "0000-0000-0000",
    "sourceIP": [],
    "tags": [],
    "variables": [],
    "venues": [
      "5e775c77-f2aa-4b0e-86c2-1798fe824825"
    ]
  },
  {
    "children": [],
    "configurations": [],
    "contacts": [],
    "created": 1672396074,
    "description": "",
    "deviceConfiguration": [],
    "deviceRules": {
      "firmwareUpgrade": "inherit",
      "rcOnly": "inherit",
      "rrm": "inherit"
    },
    "devices": [],
    "id": "56cdcd0f-0a89-4199-8f07-1fbbf8815783",
    "locations": [],
    "managementPolicies": [],
    "managementPolicy": "",
    "managementRoles": [],
    "maps": [],
    "modified": 1672396074,
    "name": "Truminds",
    "notes": [],
    "parent": "0000-0000-0000",
    "sourceIP": [],
    "tags": [],
    "variables": [],
    "venues": [
      "c0054c36-9086-4b4c-88c3-47369c1a23e3"
    ]
  },
  {
    "children": [],
    "configurations": [],
    "contacts": [],
    "created": 1672389322,
    "description": "",
    "deviceConfiguration": [],
    "deviceRules": {
      "firmwareUpgrade": "inherit",
      "rcOnly": "inherit",
      "rrm": "inherit"
    },
    "devices": [],
    "id": "0f70e61b-59f5-4fd1-905c-b0f69862933c",
    "locations": [],
    "managementPolicies": [],
    "managementPolicy": "",
    "managementRoles": [],
    "maps": [],
    "modified": 1672389322,
    "name": "BugsVerification",
    "notes": [],
    "parent": "0000-0000-0000",
    "sourceIP": [],
    "tags": [],
    "variables": [],
    "venues": [
      "1f8a29fc-e67a-487d-84ab-a546c3222cda"
    ]
  },
  {
    "children": [],
    "configurations": [],
    "contacts": [],
    "created": 1672372327,
    "description": "",
    "deviceConfiguration": [],
    "deviceRules": {
      "firmwareUpgrade": "inherit",
      "rcOnly": "inherit",
      "rrm": "inherit"
    },
    "devices": [],
    "id": "1ee2a21a-42dd-4369-a52f-02351ec9740e",
    "locations": [],
    "managementPolicies": [],
    "managementPolicy": "",
    "managementRoles": [],
    "maps": [],
    "modified": 1681938931,
    "name": "MSP R Us",
    "notes": [],
    "parent": "0000-0000-0000",
    "sourceIP": [],
    "tags": [],
    "variables": [],
    "venues": [
      "1389fde1-07a9-4f1a-bc8f-70c27e71fe74",
      "2bb691e9-b682-4690-92a8-7f0655a74e63",
      "5b8adaa1-8ced-43d7-921c-ad2feaa73a48"
    ]
  },
  {
    "children": [],
    "configurations": [],
    "contacts": [],
    "created": 1672393269,
    "description": "",
    "deviceConfiguration": [],
    "deviceRules": {
      "firmwareUpgrade": "inherit",
      "rcOnly": "inherit",
      "rrm": "inherit"
    },
    "devices": [],
    "id": "62b05999-e9f9-4559-ba63-c63ab9314859",
    "locations": [],
    "managementPolicies": [],
    "managementPolicy": "",
    "managementRoles": [],
    "maps": [],
    "modified": 1672393300,
    "name": "Rajan Org",
    "notes": [],
    "parent": "0000-0000-0000",
    "sourceIP": [],
    "tags": [],
    "variables": [],
    "venues": [
      "c90aeaf6-e1e9-448d-874f-64ab9bb85648"
    ]
  },
  {
    "children": [],
    "configurations": [],
    "contacts": [],
    "created": 1673594605,
    "description": "",
    "deviceConfiguration": [],
    "deviceRules": {
      "firmwareUpgrade": "inherit",
      "rcOnly": "inherit",
      "rrm": "inherit"
    },
    "devices": [],
    "id": "21503408-9ae7-42ad-a0c0-5188d6c32f7b",
    "locations": [],
    "managementPolicies": [],
    "managementPolicy": "",
    "managementRoles": [],
    "maps": [],
    "modified": 1673594605,
    "name": "MSP1",
    "notes": [],
    "parent": "0000-0000-0000",
    "sourceIP": [],
    "tags": [],
    "variables": [],
    "venues": [
      "9cf06f12-7c26-4d1c-b92c-ac71084bed69"
    ]
  },
  {
    "children": [],
    "configurations": [],
    "contacts": [],
    "created": 1672418151,
    "description": "",
    "deviceConfiguration": [],
    "deviceRules": {
      "firmwareUpgrade": "inherit",
      "rcOnly": "inherit",
      "rrm": "inherit"
    },
    "devices": [],
    "id": "4f467cda-3626-47af-961e-87c1d3a88358",
    "locations": [],
    "managementPolicies": [],
    "managementPolicy": "",
    "managementRoles": [],
    "maps": [],
    "modified": 1697013613,
    "name": "Gaird",
    "notes": [],
    "parent": "0000-0000-0000",
    "sourceIP": [],
    "tags": [],
    "variables": [],
    "venues": [
      "9a13c7d5-264c-4252-a5ce-dafa6cf7f63a"
    ]
  },
  {
    "children": [],
    "configurations": [],
    "contacts": [],
    "created": 1673594620,
    "description": "",
    "deviceConfiguration": [],
    "deviceRules": {
      "firmwareUpgrade": "inherit",
      "rcOnly": "inherit",
      "rrm": "inherit"
    },
    "devices": [],
    "id": "faef19c9-c218-4abd-8fba-de107d8aaef4",
    "locations": [],
    "managementPolicies": [],
    "managementPolicy": "",
    "managementRoles": [],
    "maps": [],
    "modified": 1673594620,
    "name": "MSP2",
    "notes": [],
    "parent": "0000-0000-0000",
    "sourceIP": [],
    "tags": [],
    "variables": [],
    "venues": [
      "e702fee1-00ce-46a3-bf3b-90271aaca0ea"
    ]
  },
  {
    "children": [],
    "configurations": [],
    "contacts": [],
    "created": 1678952656,
    "description": "",
    "deviceConfiguration": [],
    "deviceRules": {
      "firmwareUpgrade": "inherit",
      "rcOnly": "inherit",
      "rrm": "inherit"
    },
    "devices": [],
    "id": "f02f12b1-a7a4-44ee-982f-fc6f105df9b9",
    "locations": [],
    "managementPolicies": [],
    "managementPolicy": "",
    "managementRoles": [],
    "maps": [],
    "modified": 1679146387,
    "name": "tt1",
    "notes": [],
    "parent": "0000-0000-0000",
    "sourceIP": [],
    "tags": [],
    "variables": [],
    "venues": [
      "2b4dc417-7619-4f78-90f2-e5511721e5bd"
    ]
  },
  {
    "children": [],
    "configurations": [],
    "contacts": [],
    "created": 1673594634,
    "description": "",
    "deviceConfiguration": [],
    "deviceRules": {
      "firmwareUpgrade": "inherit",
      "rcOnly": "inherit",
      "rrm": "inherit"
    },
    "devices": [],
    "id": "6cab9439-d810-48f6-9d1e-8b963896c365",
    "locations": [],
    "managementPolicies": [],
    "managementPolicy": "",
    "managementRoles": [],
    "maps": [],
    "modified": 1673594634,
    "name": "Business1",
    "notes": [],
    "parent": "0000-0000-0000",
    "sourceIP": [],
    "tags": [],
    "variables": [],
    "venues": [
      "6355de0a-974c-4b87-9a06-b07a99a8cc3d"
    ]
  },
  {
    "children": [],
    "configurations": [],
    "contacts": [],
    "created": 1672424396,
    "description": "",
    "deviceConfiguration": [],
    "deviceRules": {
      "firmwareUpgrade": "inherit",
      "rcOnly": "inherit",
      "rrm": "inherit"
    },
    "devices": [],
    "id": "05339a26-2686-4c16-be53-4ce81bbb7eb4",
    "locations": [],
    "managementPolicies": [],
    "managementPolicy": "",
    "managementRoles": [],
    "maps": [],
    "modified": 1697013594,
    "name": "Steve Hratko",
    "notes": [],
    "parent": "0000-0000-0000",
    "sourceIP": [],
    "tags": [],
    "variables": [],
    "venues": [
      "20600f23-1d72-4cec-9e77-6967d760a527",
      "deda7a41-678b-4178-942f-133410efd95a"
    ]
  },
  {
    "children": [],
    "configurations": [],
    "contacts": [],
    "created": 1674022596,
    "description": "",
    "deviceConfiguration": [],
    "deviceRules": {
      "firmwareUpgrade": "inherit",
      "rcOnly": "inherit",
      "rrm": "inherit"
    },
    "devices": [],
    "id": "387876bc-8dc5-4610-9eb0-cee2444e5a32",
    "locations": [],
    "managementPolicies": [],
    "managementPolicy": "",
    "managementRoles": [],
    "maps": [],
    "modified": 1674022596,
    "name": "UIOPORG",
    "notes": [],
    "parent": "0000-0000-0000",
    "sourceIP": [],
    "tags": [],
    "variables": [],
    "venues": [
      "d172ccf2-a1ab-4c20-b3c8-7ccf6362eb7b"
    ]
  },
  {
    "children": [],
    "configurations": [],
    "contacts": [],
    "created": 1672645578,
    "description": "",
    "deviceConfiguration": [],
    "deviceRules": {
      "firmwareUpgrade": "inherit",
      "rcOnly": "inherit",
      "rrm": "inherit"
    },
    "devices": [],
    "id": "a6da6c19-8193-414a-ab67-0e7ebf9af1e5",
    "locations": [],
    "managementPolicies": [],
    "managementPolicy": "",
    "managementRoles": [],
    "maps": [],
    "modified": 1672645578,
    "name": "SravanAbhiram",
    "notes": [],
    "parent": "0000-0000-0000",
    "sourceIP": [],
    "tags": [],
    "variables": [],
    "venues": [
      "7156f3ab-06b5-4709-b354-6a962eab8f0d"
    ]
  },
  {
    "children": [],
    "configurations": [],
    "contacts": [],
    "created": 1673548076,
    "description": "",
    "deviceConfiguration": [],
    "deviceRules": {
      "firmwareUpgrade": "inherit",
      "rcOnly": "inherit",
      "rrm": "inherit"
    },
    "devices": [],
    "id": "2ff28146-d35a-4bd0-9c3f-f2fa93ac1294",
    "locations": [],
    "managementPolicies": [],
    "managementPolicy": "",
    "managementRoles": [],
    "maps": [],
    "modified": 1673548076,
    "name": "shasta1",
    "notes": [],
    "parent": "0000-0000-0000",
    "sourceIP": [],
    "tags": [],
    "variables": [],
    "venues": [
      "e766a39a-af13-4c49-812f-bb7fb1e26534"
    ]
  },
  {
    "children": [],
    "configurations": [],
    "contacts": [],
    "created": 1685095241,
    "description": "",
    "deviceConfiguration": [],
    "deviceRules": {
      "firmwareUpgrade": "inherit",
      "rcOnly": "inherit",
      "rrm": "inherit"
    },
    "devices": [],
    "id": "f2a411e8-afa9-46a4-a934-396c160e2a00",
    "locations": [],
    "managementPolicies": [],
    "managementPolicy": "",
    "managementRoles": [],
    "maps": [],
    "modified": 1685095241,
    "name": "infracounttest",
    "notes": [],
    "parent": "0000-0000-0000",
    "sourceIP": [],
    "tags": [],
    "variables": [],
    "venues": [
      "cedd284a-21d6-4beb-8a54-a37ee5e964fe"
    ]
  },
  {
    "children": [],
    "configurations": [],
    "contacts": [],
    "created": 1673419328,
    "description": "",
    "deviceConfiguration": [],
    "deviceRules": {
      "firmwareUpgrade": "inherit",
      "rcOnly": "inherit",
      "rrm": "inherit"
    },
    "devices": [],
    "id": "ea9cfa0d-5e37-4717-96fe-cc41cdfff41b",
    "locations": [],
    "managementPolicies": [],
    "managementPolicy": "",
    "managementRoles": [],
    "maps": [],
    "modified": 1673419328,
    "name": "MYORG3",
    "notes": [],
    "parent": "0000-0000-0000",
    "sourceIP": [],
    "tags": [],
    "variables": [],
    "venues": [
      "ae597009-065b-47fb-bb4d-e6ffc19c67e4"
    ]
  },
  {
    "children": [],
    "configurations": [],
    "contacts": [],
    "created": 1672645882,
    "description": "",
    "deviceConfiguration": [],
    "deviceRules": {
      "firmwareUpgrade": "inherit",
      "rcOnly": "inherit",
      "rrm": "inherit"
    },
    "devices": [],
    "id": "b2872afd-2d2e-4318-bb5c-30c54995f703",
    "locations": [],
    "managementPolicies": [],
    "managementPolicy": "",
    "managementRoles": [],
    "maps": [],
    "modified": 1672645882,
    "name": "SravanAbhiramYerru",
    "notes": [],
    "parent": "0000-0000-0000",
    "sourceIP": [],
    "tags": [],
    "variables": [],
    "venues": [
      "8b7d1ce4-afa8-47af-8eca-87438249c5f0",
      "c0093812-56ac-4b64-8f75-bca5a93f2dcb",
      "e8745b90-6de1-4f6f-8035-c83605ba49ea"
    ]
  },
  {
    "children": [],
    "configurations": [],
    "contacts": [],
    "created": 1674636513,
    "description": "",
    "deviceConfiguration": [],
    "deviceRules": {
      "firmwareUpgrade": "inherit",
      "rcOnly": "inherit",
      "rrm": "inherit"
    },
    "devices": [],
    "id": "ace3bef3-382a-4dd7-ba83-5d789496f5fa",
    "locations": [],
    "managementPolicies": [],
    "managementPolicy": "",
    "managementRoles": [],
    "maps": [],
    "modified": 1674639845,
    "name": "ORG NEW 12",
    "notes": [],
    "parent": "0000-0000-0000",
    "sourceIP": [],
    "tags": [],
    "variables": [],
    "venues": [
      "35551083-947b-468e-8010-29bbbb81c4bd",
      "6e01aea4-8998-4c99-ad3d-22de18cc6974"
    ]
  },
  {
    "children": [],
    "configurations": [],
    "contacts": [],
    "created": 1673419220,
    "description": "",
    "deviceConfiguration": [],
    "deviceRules": {
      "firmwareUpgrade": "inherit",
      "rcOnly": "inherit",
      "rrm": "inherit"
    },
    "devices": [],
    "id": "80b56efd-d63a-414e-a2e5-c16466cecf00",
    "locations": [],
    "managementPolicies": [],
    "managementPolicy": "",
    "managementRoles": [],
    "maps": [],
    "modified": 1673419220,
    "name": "MYORG2",
    "notes": [],
    "parent": "0000-0000-0000",
    "sourceIP": [],
    "tags": [],
    "variables": [],
    "venues": [
      "b44a113d-08e5-44bd-860f-a70564cf306b"
    ]
  },
  {
    "children": [],
    "configurations": [],
    "contacts": [],
    "created": 1672743649,
    "description": "",
    "deviceConfiguration": [],
    "deviceRules": {
      "firmwareUpgrade": "inherit",
      "rcOnly": "inherit",
      "rrm": "inherit"
    },
    "devices": [],
    "id": "d683242f-068f-4caf-85e2-0e1b06adff79",
    "locations": [],
    "managementPolicies": [],
    "managementPolicy": "",
    "managementRoles": [],
    "maps": [],
    "modified": 1672743649,
    "name": "BugsVerification",
    "notes": [],
    "parent": "0000-0000-0000",
    "sourceIP": [],
    "tags": [],
    "variables": [],
    "venues": [
      "84cb4a35-4a5e-409c-81df-10cd24ebd737"
    ]
  },
  {
    "children": [],
    "configurations": [],
    "contacts": [],
    "created": 1681199584,
    "description": "",
    "deviceConfiguration": [],
    "deviceRules": {
      "firmwareUpgrade": "inherit",
      "rcOnly": "inherit",
      "rrm": "inherit"
    },
    "devices": [],
    "id": "5c1794f7-1a91-4355-bb91-dbb600d6c43c",
    "locations": [],
    "managementPolicies": [],
    "managementPolicy": "",
    "managementRoles": [],
    "maps": [],
    "modified": 1681199584,
    "name": "alertsOrG",
    "notes": [],
    "parent": "0000-0000-0000",
    "sourceIP": [],
    "tags": [],
    "variables": [],
    "venues": [
      "8663e7fd-119f-464b-bf93-a22107affc56"
    ]
  },
  {
    "children": [],
    "configurations": [],
    "contacts": [],
    "created": 1673584951,
    "description": "",
    "deviceConfiguration": [],
    "deviceRules": {
      "firmwareUpgrade": "inherit",
      "rcOnly": "inherit",
      "rrm": "inherit"
    },
    "devices": [],
    "id": "1f35851c-e40f-4809-b95a-dc1b3704c5d1",
    "locations": [],
    "managementPolicies": [],
    "managementPolicy": "",
    "managementRoles": [],
    "maps": [],
    "modified": 1673584951,
    "name": "uk org",
    "notes": [],
    "parent": "0000-0000-0000",
    "sourceIP": [],
    "tags": [],
    "variables": [],
    "venues": [
      "2c7969ee-9158-4e7c-bf48-a43e63a80dd0",
      "f8acd0c9-20a1-4bcf-b9e0-9184b816b2f6"
    ]
  },
  {
    "children": [],
    "configurations": [],
    "contacts": [],
    "created": 1672814591,
    "description": "",
    "deviceConfiguration": [],
    "deviceRules": {
      "firmwareUpgrade": "inherit",
      "rcOnly": "inherit",
      "rrm": "inherit"
    },
    "devices": [],
    "id": "b4469c35-a1ed-4838-b60e-df962a94ad57",
    "locations": [],
    "managementPolicies": [],
    "managementPolicy": "",
    "managementRoles": [],
    "maps": [],
    "modified": 1672814591,
    "name": "BugsVerification",
    "notes": [],
    "parent": "0000-0000-0000",
    "sourceIP": [],
    "tags": [],
    "variables": [],
    "venues": [
      "8435c6fc-49b9-469e-9928-9bcb2f71bc71",
      "fd2368cb-1eef-49a0-ad4d-4a70cb233d7f"
    ]
  },
  {
    "children": [],
    "configurations": [],
    "contacts": [],
    "created": 1674639220,
    "description": "",
    "deviceConfiguration": [],
    "deviceRules": {
      "firmwareUpgrade": "inherit",
      "rcOnly": "inherit",
      "rrm": "inherit"
    },
    "devices": [],
    "id": "81617610-98ef-412c-843e-221b6c1744ae",
    "locations": [],
    "managementPolicies": [],
    "managementPolicy": "",
    "managementRoles": [],
    "maps": [],
    "modified": 1674639220,
    "name": "ORG889",
    "notes": [],
    "parent": "0000-0000-0000",
    "sourceIP": [],
    "tags": [],
    "variables": [],
    "venues": [
      "5d97481a-5c39-46af-b259-81b412b73f8e"
    ]
  },
  {
    "children": [],
    "configurations": [],
    "contacts": [],
    "created": 1672833950,
    "description": "",
    "deviceConfiguration": [],
    "deviceRules": {
      "firmwareUpgrade": "inherit",
      "rcOnly": "inherit",
      "rrm": "inherit"
    },
    "devices": [],
    "id": "2c952e52-8f02-4340-8021-d4805c6f75a0",
    "locations": [],
    "managementPolicies": [],
    "managementPolicy": "",
    "managementRoles": [],
    "maps": [],
    "modified": 1672833950,
    "name": "DELL",
    "notes": [],
    "parent": "0000-0000-0000",
    "sourceIP": [],
    "tags": [],
    "variables": [],
    "venues": [
      "368c2acd-6684-49eb-8a69-cc3750a1238b",
      "6b020f68-c5f7-4c8e-a998-81e2d5e736cb",
      "b9a42886-8166-4f47-bc17-eaa93353c330"
    ]
  },
  {
    "children": [],
    "configurations": [],
    "contacts": [],
    "created": 1672681052,
    "description": "",
    "deviceConfiguration": [],
    "deviceRules": {
      "firmwareUpgrade": "inherit",
      "rcOnly": "inherit",
      "rrm": "inherit"
    },
    "devices": [],
    "id": "21a703b2-54d7-4ff2-8ebc-cca541d207b6",
    "locations": [],
    "managementPolicies": [],
    "managementPolicy": "",
    "managementRoles": [],
    "maps": [],
    "modified": 1677758384,
    "name": "FWUpgrade Org",
    "notes": [],
    "parent": "0000-0000-0000",
    "sourceIP": [],
    "tags": [],
    "variables": [],
    "venues": [
      "15c569e9-5fd6-454b-99ac-0c2534539bb1"
    ]
  },
  {
    "children": [],
    "configurations": [],
    "contacts": [],
    "created": 1672894853,
    "description": "",
    "deviceConfiguration": [],
    "deviceRules": {
      "firmwareUpgrade": "inherit",
      "rcOnly": "inherit",
      "rrm": "inherit"
    },
    "devices": [],
    "id": "9e500450-eb34-430b-a5d7-3be7585d8b9d",
    "locations": [],
    "managementPolicies": [],
    "managementPolicy": "",
    "managementRoles": [],
    "maps": [],
    "modified": 1672894853,
    "name": "BugsVerification",
    "notes": [],
    "parent": "0000-0000-0000",
    "sourceIP": [],
    "tags": [],
    "variables": [],
    "venues": [
      "ceceb2f7-a9d3-4581-a7ae-a9776443894f"
    ]
  },
  {
    "children": [],
    "configurations": [],
    "contacts": [],
    "created": 1672895496,
    "description": "",
    "deviceConfiguration": [],
    "deviceRules": {
      "firmwareUpgrade": "inherit",
      "rcOnly": "inherit",
      "rrm": "inherit"
    },
    "devices": [],
    "id": "1cb1b310-3f71-493a-999e-56350b06afe9",
    "locations": [],
    "managementPolicies": [],
    "managementPolicy": "",
    "managementRoles": [],
    "maps": [],
    "modified": 1672895496,
    "name": "BugsVerification",
    "notes": [],
    "parent": "0000-0000-0000",
    "sourceIP": [],
    "tags": [],
    "variables": [],
    "venues": [
      "0605d608-6252-44bc-bd5b-ec0093f41b25"
    ]
  },
  {
    "children": [],
    "configurations": [],
    "contacts": [],
    "created": 1674194977,
    "description": "",
    "deviceConfiguration": [],
    "deviceRules": {
      "firmwareUpgrade": "inherit",
      "rcOnly": "inherit",
      "rrm": "inherit"
    },
    "devices": [],
    "id": "03fb477a-3d29-499c-a66e-d58901462eed",
    "locations": [],
    "managementPolicies": [],
    "managementPolicy": "",
    "managementRoles": [],
    "maps": [],
    "modified": 1674194977,
    "name": "ORG002",
    "notes": [],
    "parent": "0000-0000-0000",
    "sourceIP": [],
    "tags": [],
    "variables": [],
    "venues": [
      "33aa3aa4-2387-40ad-85d7-e3d2b54a7a27"
    ]
  },
  {
    "children": [],
    "configurations": [],
    "contacts": [],
    "created": 1673594649,
    "description": "",
    "deviceConfiguration": [],
    "deviceRules": {
      "firmwareUpgrade": "inherit",
      "rcOnly": "inherit",
      "rrm": "inherit"
    },
    "devices": [],
    "id": "fc26025c-ebb5-4f89-bdf0-5441dcdef0e0",
    "locations": [],
    "managementPolicies": [],
    "managementPolicy": "",
    "managementRoles": [],
    "maps": [],
    "modified": 1673594649,
    "name": "Business2",
    "notes": [],
    "parent": "0000-0000-0000",
    "sourceIP": [],
    "tags": [],
    "variables": [],
    "venues": [
      "775ce99e-676c-46c2-ade4-45ff1d8a38d7"
    ]
  },
  {
    "children": [],
    "configurations": [],
    "contacts": [],
    "created": 1673418878,
    "description": "",
    "deviceConfiguration": [],
    "deviceRules": {
      "firmwareUpgrade": "inherit",
      "rcOnly": "inherit",
      "rrm": "inherit"
    },
    "devices": [],
    "id": "a16ff3d9-d698-4b6a-83b7-ccf0bf403fa3",
    "locations": [],
    "managementPolicies": [],
    "managementPolicy": "",
    "managementRoles": [],
    "maps": [],
    "modified": 1673418878,
    "name": "MYORG1",
    "notes": [],
    "parent": "0000-0000-0000",
    "sourceIP": [],
    "tags": [],
    "variables": [],
    "venues": []
  },
  {
    "children": [],
    "configurations": [],
    "contacts": [],
    "created": 1682938455,
    "description": "",
    "deviceConfiguration": [],
    "deviceRules": {
      "firmwareUpgrade": "inherit",
      "rcOnly": "inherit",
      "rrm": "inherit"
    },
    "devices": [],
    "id": "b823408c-3df1-4768-b6c2-322381ca9083",
    "locations": [],
    "managementPolicies": [],
    "managementPolicy": "",
    "managementRoles": [],
    "maps": [],
    "modified": 1690785480,
    "name": "Doraemon Inc",
    "notes": [],
    "parent": "0000-0000-0000",
    "sourceIP": [],
    "tags": [],
    "variables": [],
    "venues": [
      "b36859c7-575c-4304-934e-d9d7f1d93b3c"
    ]
  },
  {
    "children": [],
    "configurations": [],
    "contacts": [],
    "created": 1686730754,
    "description": "",
    "deviceConfiguration": [],
    "deviceRules": {
      "firmwareUpgrade": "inherit",
      "rcOnly": "inherit",
      "rrm": "inherit"
    },
    "devices": [],
    "id": "5f06ed6f-197f-454c-898c-1ba64959377c",
    "locations": [],
    "managementPolicies": [],
    "managementPolicy": "",
    "managementRoles": [],
    "maps": [],
    "modified": 1686730774,
    "name": "Market",
    "notes": [],
    "parent": "0000-0000-0000",
    "sourceIP": [],
    "tags": [],
    "variables": [],
    "venues": [
      "f9788c2a-2f29-409a-8570-40a58306aaa3"
    ]
  },
  {
    "children": [],
    "configurations": [],
    "contacts": [],
    "created": 1674195901,
    "description": "",
    "deviceConfiguration": [],
    "deviceRules": {
      "firmwareUpgrade": "inherit",
      "rcOnly": "inherit",
      "rrm": "inherit"
    },
    "devices": [],
    "id": "023181d3-15a9-4613-9088-e2e6176f28b5",
    "locations": [],
    "managementPolicies": [],
    "managementPolicy": "",
    "managementRoles": [],
    "maps": [],
    "modified": 1674195901,
    "name": "ORG12",
    "notes": [],
    "parent": "0000-0000-0000",
    "sourceIP": [],
    "tags": [],
    "variables": [],
    "venues": [
      "74fb60d4-aba7-4a9f-9208-fd523c051a3d"
    ]
  },
  {
    "children": [],
    "configurations": [],
    "contacts": [],
    "created": 1686722700,
    "description": "",
    "deviceConfiguration": [],
    "deviceRules": {
      "firmwareUpgrade": "inherit",
      "rcOnly": "inherit",
      "rrm": "inherit"
    },
    "devices": [],
    "id": "5c659f19-5ce6-4dd2-9987-5d49d677bb54",
    "locations": [],
    "managementPolicies": [],
    "managementPolicy": "",
    "managementRoles": [],
    "maps": [],
    "modified": 1697099329,
    "name": "fortest1hjgvhvjwew",
    "notes": [],
    "parent": "0000-0000-0000",
    "sourceIP": [],
    "tags": [],
    "variables": [],
    "venues": [
      "cfe7d1b2-64db-4d08-9c1a-28806b4f43fe"
    ]
  },
  {
    "children": [],
    "configurations": [],
    "contacts": [],
    "created": 1674636366,
    "description": "",
    "deviceConfiguration": [],
    "deviceRules": {
      "firmwareUpgrade": "inherit",
      "rcOnly": "inherit",
      "rrm": "inherit"
    },
    "devices": [],
    "id": "de240bf6-5b1a-41c1-9a7c-df33363d62fe",
    "locations": [],
    "managementPolicies": [],
    "managementPolicy": "",
    "managementRoles": [],
    "maps": [],
    "modified": 1674638497,
    "name": "ORG750",
    "notes": [],
    "parent": "0000-0000-0000",
    "sourceIP": [],
    "tags": [],
    "variables": [],
    "venues": []
  },
  {
    "children": [],
    "configurations": [],
    "contacts": [],
    "created": 1674463247,
    "description": "",
    "deviceConfiguration": [],
    "deviceRules": {
      "firmwareUpgrade": "inherit",
      "rcOnly": "inherit",
      "rrm": "inherit"
    },
    "devices": [],
    "id": "2beea10f-2eb3-4cf5-8560-906fde3d4849",
    "locations": [],
    "managementPolicies": [],
    "managementPolicy": "",
    "managementRoles": [],
    "maps": [],
    "modified": 1674463247,
    "name": "ORG7745",
    "notes": [],
    "parent": "0000-0000-0000",
    "sourceIP": [],
    "tags": [],
    "variables": [],
    "venues": []
  },
  {
    "children": [],
    "configurations": [],
    "contacts": [],
    "created": 1674643302,
    "description": "",
    "deviceConfiguration": [],
    "deviceRules": {
      "firmwareUpgrade": "inherit",
      "rcOnly": "inherit",
      "rrm": "inherit"
    },
    "devices": [],
    "id": "77427889-5982-4d4e-9d6d-6af4cdf38ce6",
    "locations": [],
    "managementPolicies": [],
    "managementPolicy": "",
    "managementRoles": [],
    "maps": [],
    "modified": 1674643302,
    "name": "DElete later",
    "notes": [],
    "parent": "0000-0000-0000",
    "sourceIP": [],
    "tags": [],
    "variables": [],
    "venues": [
      "01735afb-65a8-4ea9-aa82-b9727e9d20ab"
    ]
  },
  {
    "children": [],
    "configurations": [],
    "contacts": [],
    "created": 1674801581,
    "description": "",
    "deviceConfiguration": [],
    "deviceRules": {
      "firmwareUpgrade": "inherit",
      "rcOnly": "inherit",
      "rrm": "inherit"
    },
    "devices": [],
    "id": "358a4aa0-d48d-4df1-9a53-88cb0bf0673d",
    "locations": [],
    "managementPolicies": [],
    "managementPolicy": "",
    "managementRoles": [],
    "maps": [],
    "modified": 1674801581,
    "name": "ORG34",
    "notes": [],
    "parent": "0000-0000-0000",
    "sourceIP": [],
    "tags": [],
    "variables": [],
    "venues": [
      "266371ed-ea27-4ef5-bec4-99dfa54de5a6"
    ]
  },
  {
    "children": [],
    "configurations": [],
    "contacts": [],
    "created": 1674802011,
    "description": "",
    "deviceConfiguration": [],
    "deviceRules": {
      "firmwareUpgrade": "inherit",
      "rcOnly": "inherit",
      "rrm": "inherit"
    },
    "devices": [],
    "id": "90c9bd6b-78da-445a-9e05-4232c5154eaf",
    "locations": [],
    "managementPolicies": [],
    "managementPolicy": "",
    "managementRoles": [],
    "maps": [],
    "modified": 1674802011,
    "name": "AORG23",
    "notes": [],
    "parent": "0000-0000-0000",
    "sourceIP": [],
    "tags": [],
    "variables": [],
    "venues": [
      "f19fa87d-96d9-4c20-8ceb-aaac0db17a6b"
    ]
  },
  {
    "children": [],
    "configurations": [],
    "contacts": [],
    "created": 1674639352,
    "description": "",
    "deviceConfiguration": [],
    "deviceRules": {
      "firmwareUpgrade": "inherit",
      "rcOnly": "inherit",
      "rrm": "inherit"
    },
    "devices": [],
    "id": "a493abc2-9f53-49e1-b7ae-f0b964604fb3",
    "locations": [],
    "managementPolicies": [],
    "managementPolicy": "",
    "managementRoles": [],
    "maps": [],
    "modified": 1674639352,
    "name": "ORG0045",
    "notes": [],
    "parent": "0000-0000-0000",
    "sourceIP": [],
    "tags": [],
    "variables": [],
    "venues": [
      "ad23fc2b-018a-4b83-9399-4673cd6d8835"
    ]
  },
  {
    "children": [],
    "configurations": [],
    "contacts": [],
    "created": 1672897824,
    "description": "",
    "deviceConfiguration": [],
    "deviceRules": {
      "firmwareUpgrade": "inherit",
      "rcOnly": "inherit",
      "rrm": "inherit"
    },
    "devices": [],
    "id": "180f8248-3fba-4c93-857a-75536a06aef7",
    "locations": [],
    "managementPolicies": [],
    "managementPolicy": "",
    "managementRoles": [],
    "maps": [],
    "modified": 1672897824,
    "name": "Dummy Org",
    "notes": [],
    "parent": "0000-0000-0000",
    "sourceIP": [],
    "tags": [],
    "variables": [],
    "venues": [
      "b31e9a91-b9a7-48a6-bb1c-5f9ae7bfc5b9"
    ]
  },
  {
    "children": [],
    "configurations": [],
    "contacts": [],
    "created": 1673249134,
    "description": "",
    "deviceConfiguration": [],
    "deviceRules": {
      "firmwareUpgrade": "inherit",
      "rcOnly": "inherit",
      "rrm": "inherit"
    },
    "devices": [],
    "id": "7f528508-09aa-46cb-9d94-ec19ea018fc1",
    "locations": [],
    "managementPolicies": [],
    "managementPolicy": "",
    "managementRoles": [],
    "maps": [],
    "modified": 1673249134,
    "name": "WorkflowTesting",
    "notes": [],
    "parent": "0000-0000-0000",
    "sourceIP": [],
    "tags": [],
    "variables": [],
    "venues": [
      "7eb4603d-0fb1-48c7-a2b8-aee6db1b3766"
    ]
  },
  {
    "children": [],
    "configurations": [],
    "contacts": [],
    "created": 1673432332,
    "description": "",
    "deviceConfiguration": [],
    "deviceRules": {
      "firmwareUpgrade": "inherit",
      "rcOnly": "inherit",
      "rrm": "inherit"
    },
    "devices": [],
    "id": "5713a17e-0188-4180-b479-062df03ad3d6",
    "locations": [],
    "managementPolicies": [],
    "managementPolicy": "",
    "managementRoles": [],
    "maps": [],
    "modified": 1673432332,
    "name": "TEST45",
    "notes": [],
    "parent": "0000-0000-0000",
    "sourceIP": [],
    "tags": [],
    "variables": [],
    "venues": [
      "c3b1b78c-3518-4430-8054-66a579c004d6"
    ]
  },
  {
    "children": [],
    "configurations": [],
    "contacts": [],
    "created": 1674643530,
    "description": "",
    "deviceConfiguration": [],
    "deviceRules": {
      "firmwareUpgrade": "inherit",
      "rcOnly": "inherit",
      "rrm": "inherit"
    },
    "devices": [],
    "id": "959b2271-afc4-4d40-9e16-80b13957c613",
    "locations": [],
    "managementPolicies": [],
    "managementPolicy": "",
    "managementRoles": [],
    "maps": [],
    "modified": 1674643530,
    "name": "DEleteLater",
    "notes": [],
    "parent": "0000-0000-0000",
    "sourceIP": [],
    "tags": [],
    "variables": [],
    "venues": [
      "3768d358-e140-4e05-bf94-53c9aa3261e0"
    ]
  },
  {
    "children": [],
    "configurations": [],
    "contacts": [],
    "created": 1674199417,
    "description": "",
    "deviceConfiguration": [],
    "deviceRules": {
      "firmwareUpgrade": "inherit",
      "rcOnly": "inherit",
      "rrm": "inherit"
    },
    "devices": [],
    "id": "afe6ffe0-2be5-475e-9286-8c84a11dc05c",
    "locations": [],
    "managementPolicies": [],
    "managementPolicy": "",
    "managementRoles": [],
    "maps": [],
    "modified": 1674199417,
    "name": "ORG251",
    "notes": [],
    "parent": "0000-0000-0000",
    "sourceIP": [],
    "tags": [],
    "variables": [],
    "venues": []
  },
  {
    "children": [],
    "configurations": [],
    "contacts": [],
    "created": 1673598743,
    "description": "",
    "deviceConfiguration": [],
    "deviceRules": {
      "firmwareUpgrade": "inherit",
      "rcOnly": "inherit",
      "rrm": "inherit"
    },
    "devices": [],
    "id": "012bd0cc-1de6-4b1a-ae08-6d853a743c90",
    "locations": [],
    "managementPolicies": [],
    "managementPolicy": "",
    "managementRoles": [],
    "maps": [],
    "modified": 1673599453,
    "name": "ORGZ1",
    "notes": [],
    "parent": "0000-0000-0000",
    "sourceIP": [],
    "tags": [],
    "variables": [],
    "venues": [
      "71657159-0310-4f9a-beb0-2b74f6647ab3"
    ]
  },
  {
    "children": [],
    "configurations": [],
    "contacts": [],
    "created": 1674199393,
    "description": "",
    "deviceConfiguration": [],
    "deviceRules": {
      "firmwareUpgrade": "inherit",
      "rcOnly": "inherit",
      "rrm": "inherit"
    },
    "devices": [],
    "id": "64dae97b-fa43-4d17-8278-569f176f1d35",
    "locations": [],
    "managementPolicies": [],
    "managementPolicy": "",
    "managementRoles": [],
    "maps": [],
    "modified": 1674199393,
    "name": "ORG250",
    "notes": [],
    "parent": "0000-0000-0000",
    "sourceIP": [],
    "tags": [],
    "variables": [],
    "venues": []
  },
  {
    "children": [],
    "configurations": [],
    "contacts": [],
    "created": 1673597379,
    "description": "",
    "deviceConfiguration": [],
    "deviceRules": {
      "firmwareUpgrade": "inherit",
      "rcOnly": "inherit",
      "rrm": "inherit"
    },
    "devices": [],
    "id": "eb31f590-b08c-4bde-9bfa-2ddb79cc1780",
    "locations": [],
    "managementPolicies": [],
    "managementPolicy": "",
    "managementRoles": [],
    "maps": [],
    "modified": 1673597379,
    "name": "ORG089",
    "notes": [],
    "parent": "0000-0000-0000",
    "sourceIP": [],
    "tags": [],
    "variables": [],
    "venues": [
      "30d7616c-d2ec-4919-a7e3-d2f91fbe41e8",
      "b22d8aa8-9a42-48c8-8735-12f38fe06fad"
    ]
  },
  {
    "children": [],
    "configurations": [],
    "contacts": [],
    "created": 1674802280,
    "description": "",
    "deviceConfiguration": [],
    "deviceRules": {
      "firmwareUpgrade": "inherit",
      "rcOnly": "inherit",
      "rrm": "inherit"
    },
    "devices": [],
    "id": "a9856f87-ea44-48bb-9d27-4815581a79d8",
    "locations": [],
    "managementPolicies": [],
    "managementPolicy": "",
    "managementRoles": [],
    "maps": [],
    "modified": 1674802280,
    "name": "AORG2345",
    "notes": [],
    "parent": "0000-0000-0000",
    "sourceIP": [],
    "tags": [],
    "variables": [],
    "venues": [
      "09d327b3-c825-4704-a101-57bfff21ee8a"
    ]
  },
  {
    "children": [],
    "configurations": [],
    "contacts": [],
    "created": 1674802782,
    "description": "",
    "deviceConfiguration": [],
    "deviceRules": {
      "firmwareUpgrade": "inherit",
      "rcOnly": "inherit",
      "rrm": "inherit"
    },
    "devices": [],
    "id": "adee87b3-ad2d-46ff-816d-257da0fd8ed0",
    "locations": [],
    "managementPolicies": [],
    "managementPolicy": "",
    "managementRoles": [],
    "maps": [],
    "modified": 1674802782,
    "name": "ORG56",
    "notes": [],
    "parent": "0000-0000-0000",
    "sourceIP": [],
    "tags": [],
    "variables": [],
    "venues": [
      "67b17d4b-46e4-4a54-a4f9-8cd4c568b436"
    ]
  },
  {
    "children": [],
    "configurations": [],
    "contacts": [],
    "created": 1678084208,
    "description": "",
    "deviceConfiguration": [],
    "deviceRules": {
      "firmwareUpgrade": "inherit",
      "rcOnly": "inherit",
      "rrm": "inherit"
    },
    "devices": [],
    "id": "16333acb-90d5-4aaf-805c-e433350b55d4",
    "locations": [],
    "managementPolicies": [],
    "managementPolicy": "",
    "managementRoles": [],
    "maps": [],
    "modified": 1678084208,
    "name": "Import Org",
    "notes": [],
    "parent": "0000-0000-0000",
    "sourceIP": [],
    "tags": [],
    "variables": [],
    "venues": [
      "75fb641c-f9f6-4e95-80a8-240270a699e5"
    ]
  },
  {
    "children": [],
    "configurations": [],
    "contacts": [],
    "created": 1694704113,
    "description": "",
    "deviceConfiguration": [],
    "deviceRules": {
      "firmwareUpgrade": "inherit",
      "rcOnly": "inherit",
      "rrm": "inherit"
    },
    "devices": [],
    "id": "d0a283e7-e70d-4ea0-b433-9127d03382ca",
    "locations": [],
    "managementPolicies": [],
    "managementPolicy": "",
    "managementRoles": [],
    "maps": [],
    "modified": 1694704113,
    "name": "1testtest",
    "notes": [],
    "parent": "0000-0000-0000",
    "sourceIP": [],
    "tags": [],
    "variables": [],
    "venues": [
      "c6650095-12b2-41f3-821c-c42d5f453572"
    ]
  },
  {
    "children": [],
    "configurations": [],
    "contacts": [],
    "created": 1674803055,
    "description": "",
    "deviceConfiguration": [],
    "deviceRules": {
      "firmwareUpgrade": "inherit",
      "rcOnly": "inherit",
      "rrm": "inherit"
    },
    "devices": [],
    "id": "44985b72-0860-43f0-b68a-365c4a3124ff",
    "locations": [],
    "managementPolicies": [],
    "managementPolicy": "",
    "managementRoles": [],
    "maps": [],
    "modified": 1674803055,
    "name": "ORG567",
    "notes": [],
    "parent": "0000-0000-0000",
    "sourceIP": [],
    "tags": [],
    "variables": [],
    "venues": [
      "0415115b-9c53-4b85-b088-d0d672fa3142",
      "14a1de23-c31b-4567-9689-8afefaff8bab"
    ]
  },
  {
    "children": [],
    "configurations": [],
    "contacts": [],
    "created": 1674818200,
    "description": "",
    "deviceConfiguration": [],
    "deviceRules": {
      "firmwareUpgrade": "inherit",
      "rcOnly": "inherit",
      "rrm": "inherit"
    },
    "devices": [],
    "id": "cc07fdd9-43d1-4089-a213-6278fe530e41",
    "locations": [],
    "managementPolicies": [],
    "managementPolicy": "",
    "managementRoles": [],
    "maps": [],
    "modified": 1674818200,
    "name": "NEWORG23",
    "notes": [],
    "parent": "0000-0000-0000",
    "sourceIP": [],
    "tags": [],
    "variables": [],
    "venues": [
      "981a07b2-aa94-4894-80a8-d9b3b5c79e53"
    ]
  },
  {
    "children": [],
    "configurations": [],
    "contacts": [],
    "created": 1674819297,
    "description": "",
    "deviceConfiguration": [],
    "deviceRules": {
      "firmwareUpgrade": "inherit",
      "rcOnly": "inherit",
      "rrm": "inherit"
    },
    "devices": [],
    "id": "59b50c79-9b1a-4e2e-8a5b-1301c41638d0",
    "locations": [],
    "managementPolicies": [],
    "managementPolicy": "",
    "managementRoles": [],
    "maps": [],
    "modified": 1674819297,
    "name": "NEWORG23",
    "notes": [],
    "parent": "0000-0000-0000",
    "sourceIP": [],
    "tags": [],
    "variables": [],
    "venues": [
      "3f8b9e75-c653-45bb-bd97-a6a0e972aca3"
    ]
  },
  {
    "children": [],
    "configurations": [],
    "contacts": [],
    "created": 1675063528,
    "description": "",
    "deviceConfiguration": [],
    "deviceRules": {
      "firmwareUpgrade": "inherit",
      "rcOnly": "inherit",
      "rrm": "inherit"
    },
    "devices": [],
    "id": "5e8fb36c-7972-4416-aa74-440e52bef57f",
    "locations": [],
    "managementPolicies": [],
    "managementPolicy": "",
    "managementRoles": [],
    "maps": [],
    "modified": 1675063528,
    "name": "Delete Later",
    "notes": [],
    "parent": "0000-0000-0000",
    "sourceIP": [],
    "tags": [],
    "variables": [],
    "venues": [
      "6a831bbd-1bad-46a6-b18e-88305aba40ed"
    ]
  },
  {
    "children": [],
    "configurations": [],
    "contacts": [],
    "created": 1675075539,
    "description": "",
    "deviceConfiguration": [],
    "deviceRules": {
      "firmwareUpgrade": "inherit",
      "rcOnly": "inherit",
      "rrm": "inherit"
    },
    "devices": [],
    "id": "b54aa120-484b-47df-ad6d-0cdfadbb4336",
    "locations": [],
    "managementPolicies": [],
    "managementPolicy": "",
    "managementRoles": [],
    "maps": [],
    "modified": 1675075539,
    "name": "Delete Later",
    "notes": [],
    "parent": "0000-0000-0000",
    "sourceIP": [],
    "tags": [],
    "variables": [],
    "venues": [
      "f3359f9a-868e-480a-887f-db9c8e93b7ad"
    ]
  },
  {
    "children": [],
    "configurations": [],
    "contacts": [],
    "created": 1675082270,
    "description": "",
    "deviceConfiguration": [],
    "deviceRules": {
      "firmwareUpgrade": "inherit",
      "rcOnly": "inherit",
      "rrm": "inherit"
    },
    "devices": [],
    "id": "4af4c781-a287-4046-8d03-253d537cf1e2",
    "locations": [],
    "managementPolicies": [],
    "managementPolicy": "",
    "managementRoles": [],
    "maps": [],
    "modified": 1675082270,
    "name": "Delete",
    "notes": [],
    "parent": "0000-0000-0000",
    "sourceIP": [],
    "tags": [],
    "variables": [],
    "venues": [
      "76ccde72-9e08-4e8f-9e40-73eff482c9df"
    ]
  },
  {
    "children": [],
    "configurations": [],
    "contacts": [],
    "created": 1675409870,
    "description": "",
    "deviceConfiguration": [],
    "deviceRules": {
      "firmwareUpgrade": "inherit",
      "rcOnly": "inherit",
      "rrm": "inherit"
    },
    "devices": [],
    "id": "6914bc75-b81c-4ee4-8cf7-82ed09dcdbc8",
    "locations": [],
    "managementPolicies": [],
    "managementPolicy": "",
    "managementRoles": [],
    "maps": [],
    "modified": 1675409870,
    "name": "Import Infra",
    "notes": [],
    "parent": "0000-0000-0000",
    "sourceIP": [],
    "tags": [],
    "variables": [],
    "venues": [
      "f245ff72-ab56-46c2-99af-9ea0b2741e1b"
    ]
  },
  {
    "children": [],
    "configurations": [],
    "contacts": [],
    "created": 1675409993,
    "description": "",
    "deviceConfiguration": [],
    "deviceRules": {
      "firmwareUpgrade": "inherit",
      "rcOnly": "inherit",
      "rrm": "inherit"
    },
    "devices": [],
    "id": "25f1a8da-ea4a-42f4-8e77-0f77180a9764",
    "locations": [],
    "managementPolicies": [],
    "managementPolicy": "",
    "managementRoles": [],
    "maps": [],
    "modified": 1675409993,
    "name": "Import Infra",
    "notes": [],
    "parent": "0000-0000-0000",
    "sourceIP": [],
    "tags": [],
    "variables": [],
    "venues": [
      "89e0ddc0-9d92-4f75-9aa1-c86ce2cf24c5"
    ]
  },
  {
    "children": [],
    "configurations": [],
    "contacts": [],
    "created": 1675415183,
    "description": "",
    "deviceConfiguration": [],
    "deviceRules": {
      "firmwareUpgrade": "inherit",
      "rcOnly": "inherit",
      "rrm": "inherit"
    },
    "devices": [],
    "id": "a8464ca6-fa09-4fd7-9424-329555f68dee",
    "locations": [],
    "managementPolicies": [],
    "managementPolicy": "",
    "managementRoles": [],
    "maps": [],
    "modified": 1675415183,
    "name": "Rohit Kumar",
    "notes": [],
    "parent": "0000-0000-0000",
    "sourceIP": [],
    "tags": [],
    "variables": [],
    "venues": [
      "9f85d751-d3dd-4e66-84fc-9a5e2ab3fb76"
    ]
  },
  {
    "children": [],
    "configurations": [],
    "contacts": [],
    "created": 1675416818,
    "description": "",
    "deviceConfiguration": [],
    "deviceRules": {
      "firmwareUpgrade": "inherit",
      "rcOnly": "inherit",
      "rrm": "inherit"
    },
    "devices": [],
    "id": "f244a74a-8734-4398-9096-0171d1c7a932",
    "locations": [],
    "managementPolicies": [],
    "managementPolicy": "",
    "managementRoles": [],
    "maps": [],
    "modified": 1675416818,
    "name": "Avijit Ghosh",
    "notes": [],
    "parent": "0000-0000-0000",
    "sourceIP": [],
    "tags": [],
    "variables": [],
    "venues": [
      "2975db1f-2a0b-4797-8a0f-79b8091c770e"
    ]
  },
  {
    "children": [],
    "configurations": [],
    "contacts": [],
    "created": 1675666713,
    "description": "",
    "deviceConfiguration": [],
    "deviceRules": {
      "firmwareUpgrade": "inherit",
      "rcOnly": "inherit",
      "rrm": "inherit"
    },
    "devices": [],
    "id": "f606392c-d5de-493e-a9f7-78a1e22660c4",
    "locations": [],
    "managementPolicies": [],
    "managementPolicy": "",
    "managementRoles": [],
    "maps": [],
    "modified": 1675666713,
    "name": "Import",
    "notes": [],
    "parent": "0000-0000-0000",
    "sourceIP": [],
    "tags": [],
    "variables": [],
    "venues": [
      "90c1099c-b53d-4b4c-9c25-e024d364fbbe"
    ]
  },
  {
    "children": [],
    "configurations": [],
    "contacts": [],
    "created": 1675668002,
    "description": "",
    "deviceConfiguration": [],
    "deviceRules": {
      "firmwareUpgrade": "inherit",
      "rcOnly": "inherit",
      "rrm": "inherit"
    },
    "devices": [],
    "id": "b755e5df-3100-4ec7-ad5b-dc2b36c743f8",
    "locations": [],
    "managementPolicies": [],
    "managementPolicy": "",
    "managementRoles": [],
    "maps": [],
    "modified": 1675668002,
    "name": "Import",
    "notes": [],
    "parent": "0000-0000-0000",
    "sourceIP": [],
    "tags": [],
    "variables": [],
    "venues": [
      "cc1a57b1-e97b-4b3d-8009-b38b63ec4197"
    ]
  },
  {
    "children": [],
    "configurations": [],
    "contacts": [],
    "created": 1675746928,
    "description": "",
    "deviceConfiguration": [],
    "deviceRules": {
      "firmwareUpgrade": "inherit",
      "rcOnly": "inherit",
      "rrm": "inherit"
    },
    "devices": [],
    "id": "80451a86-74d1-4e3e-b9eb-e6941d782dbf",
    "locations": [],
    "managementPolicies": [],
    "managementPolicy": "",
    "managementRoles": [],
    "maps": [],
    "modified": 1675746928,
    "name": "Import",
    "notes": [],
    "parent": "0000-0000-0000",
    "sourceIP": [],
    "tags": [],
    "variables": [],
    "venues": [
      "27a48566-831d-496d-a416-020dad374530"
    ]
  },
  {
    "children": [],
    "configurations": [],
    "contacts": [],
    "created": 1675686829,
    "description": "",
    "deviceConfiguration": [],
    "deviceRules": {
      "firmwareUpgrade": "inherit",
      "rcOnly": "inherit",
      "rrm": "inherit"
    },
    "devices": [],
    "id": "5480c343-6b2e-4f6b-97fb-743d9f918dc5",
    "locations": [],
    "managementPolicies": [],
    "managementPolicy": "",
    "managementRoles": [],
    "maps": [],
    "modified": 1675686829,
    "name": "New Org",
    "notes": [],
    "parent": "0000-0000-0000",
    "sourceIP": [],
    "tags": [],
    "variables": [],
    "venues": [
      "1bedda4b-4783-4965-9c41-cea8ea388de5",
      "405f6051-7b62-47b6-9a46-c200ed53c7f4"
    ]
  },
  {
    "children": [],
    "configurations": [],
    "contacts": [],
    "created": 1675666366,
    "description": "",
    "deviceConfiguration": [],
    "deviceRules": {
      "firmwareUpgrade": "inherit",
      "rcOnly": "inherit",
      "rrm": "inherit"
    },
    "devices": [],
    "id": "3f0728f1-0286-4e79-a150-d1c599e39685",
    "locations": [],
    "managementPolicies": [],
    "managementPolicy": "",
    "managementRoles": [],
    "maps": [],
    "modified": 1675666366,
    "name": "Import INfra 1",
    "notes": [],
    "parent": "0000-0000-0000",
    "sourceIP": [],
    "tags": [],
    "variables": [],
    "venues": [
      "00de94f0-b7b5-40ac-874c-442b0b41bcf3"
    ]
  },
  {
    "children": [],
    "configurations": [],
    "contacts": [],
    "created": 1675868935,
    "description": "",
    "deviceConfiguration": [],
    "deviceRules": {
      "firmwareUpgrade": "inherit",
      "rcOnly": "inherit",
      "rrm": "inherit"
    },
    "devices": [],
    "id": "f3c93af2-0e20-49af-958d-5491ca5ef43a",
    "locations": [],
    "managementPolicies": [],
    "managementPolicy": "",
    "managementRoles": [],
    "maps": [],
    "modified": 1675868935,
    "name": "Demo",
    "notes": [],
    "parent": "0000-0000-0000",
    "sourceIP": [],
    "tags": [],
    "variables": [],
    "venues": [
      "3e19af54-7fe7-4a78-86e5-842169886e24",
      "e7272047-d259-484b-85d1-61c56da88b6f"
    ]
  },
  {
    "children": [],
    "configurations": [],
    "contacts": [],
    "created": 1676289598,
    "description": "",
    "deviceConfiguration": [],
    "deviceRules": {
      "firmwareUpgrade": "inherit",
      "rcOnly": "inherit",
      "rrm": "inherit"
    },
    "devices": [],
    "id": "c585231f-a2a1-4594-9ab6-c944a8820364",
    "locations": [],
    "managementPolicies": [],
    "managementPolicy": "",
    "managementRoles": [],
    "maps": [],
    "modified": 1676289598,
    "name": "apm-go",
    "notes": [],
    "parent": "0000-0000-0000",
    "sourceIP": [],
    "tags": [],
    "variables": [],
    "venues": [
      "dd4d4cd2-18d9-4c0d-a069-25863246b808"
    ]
  },
  {
    "children": [],
    "configurations": [],
    "contacts": [],
    "created": 1676973237,
    "description": "",
    "deviceConfiguration": [],
    "deviceRules": {
      "firmwareUpgrade": "inherit",
      "rcOnly": "inherit",
      "rrm": "inherit"
    },
    "devices": [],
    "id": "c4e2a897-3d3a-476f-87d4-798f3d7e6bdd",
    "locations": [],
    "managementPolicies": [],
    "managementPolicy": "",
    "managementRoles": [],
    "maps": [],
    "modified": 1676973237,
    "name": "Serhiy Pshyk",
    "notes": [],
    "parent": "0000-0000-0000",
    "sourceIP": [],
    "tags": [],
    "variables": [],
    "venues": [
      "98a7f0fc-1732-41b8-9a09-7fb0a6279cd3"
    ]
  },
  {
    "children": [],
    "configurations": [],
    "contacts": [],
    "created": 1676975658,
    "description": "",
    "deviceConfiguration": [],
    "deviceRules": {
      "firmwareUpgrade": "inherit",
      "rcOnly": "inherit",
      "rrm": "inherit"
    },
    "devices": [],
    "id": "7da9202c-eac1-4f2e-8782-1994d8782d41",
    "locations": [],
    "managementPolicies": [],
    "managementPolicy": "",
    "managementRoles": [],
    "maps": [],
    "modified": 1676975658,
    "name": "Taras Chornyi",
    "notes": [],
    "parent": "0000-0000-0000",
    "sourceIP": [],
    "tags": [],
    "variables": [],
    "venues": [
      "229d7703-537a-4738-b94d-67723ed2e283",
      "3de33828-aa67-47b3-824a-0467ea54317c",
      "66ea6cd1-5768-4c7b-9804-f5931ee4f9f4",
      "9aeed19f-64a2-4949-b203-4245fd3b8bd1"
    ]
  },
  {
    "children": [],
    "configurations": [],
    "contacts": [],
    "created": 1696583206,
    "description": "",
    "deviceConfiguration": [],
    "deviceRules": {
      "firmwareUpgrade": "inherit",
      "rcOnly": "inherit",
      "rrm": "inherit"
    },
    "devices": [],
    "id": "761171f8-309e-440c-a0e9-90ed7a0aea51",
    "locations": [],
    "managementPolicies": [],
    "managementPolicy": "",
    "managementRoles": [],
    "maps": [],
    "modified": 1696583206,
    "name": "tobedeleted",
    "notes": [],
    "parent": "0000-0000-0000",
    "sourceIP": [],
    "tags": [],
    "variables": [],
    "venues": [
      "005c1f29-9acd-4aeb-bd83-139fefc05f8e"
    ]
  },
  {
    "children": [],
    "configurations": [],
    "contacts": [],
    "created": 1676975018,
    "description": "",
    "deviceConfiguration": [],
    "deviceRules": {
      "firmwareUpgrade": "inherit",
      "rcOnly": "inherit",
      "rrm": "inherit"
    },
    "devices": [],
    "id": "d730fb19-f17e-4f66-85eb-752ef0680743",
    "locations": [],
    "managementPolicies": [],
    "managementPolicy": "",
    "managementRoles": [],
    "maps": [],
    "modified": 1676975018,
    "name": "PLVision",
    "notes": [],
    "parent": "0000-0000-0000",
    "sourceIP": [],
    "tags": [],
    "variables": [],
    "venues": [
      "d004601c-6f0e-4384-8243-a882ca9f3f89",
      "fb834f93-e32d-4214-9c82-2228c0b2af58"
    ]
  },
  {
    "children": [],
    "configurations": [],
    "contacts": [],
    "created": 1679473045,
    "description": "",
    "deviceConfiguration": [],
    "deviceRules": {
      "firmwareUpgrade": "inherit",
      "rcOnly": "inherit",
      "rrm": "inherit"
    },
    "devices": [],
    "id": "99f0438a-62a7-4aae-af1c-37ff952e9c34",
    "locations": [],
    "managementPolicies": [],
    "managementPolicy": "",
    "managementRoles": [],
    "maps": [],
    "modified": 1679473045,
    "name": "Jagannath",
    "notes": [],
    "parent": "0000-0000-0000",
    "sourceIP": [],
    "tags": [],
    "variables": [],
    "venues": [
      "09f8cd6b-33e2-4e8d-a2e1-4f269fbd4710",
      "5c486f9d-b1a1-4211-8eba-17ccca8adf49",
      "e4afb38f-634b-4e58-8bee-8961d17ab3cd"
    ]
  },
  {
    "children": [],
    "configurations": [],
    "contacts": [],
    "created": 1674044405,
    "description": "",
    "deviceConfiguration": [],
    "deviceRules": {
      "firmwareUpgrade": "inherit",
      "rcOnly": "inherit",
      "rrm": "inherit"
    },
    "devices": [],
    "id": "80e5fcfb-9293-4ad1-ac57-4764aac779d2",
    "locations": [],
    "managementPolicies": [],
    "managementPolicy": "",
    "managementRoles": [],
    "maps": [],
    "modified": 1674044405,
    "name": "Binny",
    "notes": [],
    "parent": "0000-0000-0000",
    "sourceIP": [],
    "tags": [],
    "variables": [],
    "venues": [
      "666df8e2-efe5-4d44-a97b-364a0e8616f0"
    ]
  },
  {
    "children": [],
    "configurations": [],
    "contacts": [],
    "created": 1674105685,
    "description": "",
    "deviceConfiguration": [],
    "deviceRules": {
      "firmwareUpgrade": "inherit",
      "rcOnly": "inherit",
      "rrm": "inherit"
    },
    "devices": [],
    "id": "18fab76d-0273-48a2-ace7-acf849d84002",
    "locations": [],
    "managementPolicies": [],
    "managementPolicy": "",
    "managementRoles": [],
    "maps": [],
    "modified": 1674105685,
    "name": "ORGTESR",
    "notes": [],
    "parent": "0000-0000-0000",
    "sourceIP": [],
    "tags": [],
    "variables": [],
    "venues": [
      "2ca91504-3d84-41c2-a2e5-e74b4e0e2455"
    ]
  },
  {
    "children": [],
    "configurations": [],
    "contacts": [],
    "created": 1673254564,
    "description": "",
    "deviceConfiguration": [],
    "deviceRules": {
      "firmwareUpgrade": "inherit",
      "rcOnly": "inherit",
      "rrm": "inherit"
    },
    "devices": [],
    "id": "52333b77-abea-48c0-aab1-599638740789",
    "locations": [],
    "managementPolicies": [],
    "managementPolicy": "",
    "managementRoles": [],
    "maps": [],
    "modified": 1673254564,
    "name": "SRAVAN",
    "notes": [],
    "parent": "0000-0000-0000",
    "sourceIP": [],
    "tags": [],
    "variables": [],
    "venues": [
      "89a4d3e5-a59c-498c-807f-5b333bf824aa"
    ]
  },
  {
    "children": [],
    "configurations": [],
    "contacts": [],
    "created": 1673626081,
    "description": "",
    "deviceConfiguration": [],
    "deviceRules": {
      "firmwareUpgrade": "inherit",
      "rcOnly": "inherit",
      "rrm": "inherit"
    },
    "devices": [],
    "id": "8fcc9c9b-a23d-4e9a-aa7b-ae12c9d7ec55",
    "locations": [],
    "managementPolicies": [],
    "managementPolicy": "",
    "managementRoles": [],
    "maps": [],
    "modified": 1673626081,
    "name": "ORG0022",
    "notes": [],
    "parent": "0000-0000-0000",
    "sourceIP": [],
    "tags": [],
    "variables": [],
    "venues": []
  },
  {
    "children": [],
    "configurations": [],
    "contacts": [],
    "created": 1674643776,
    "description": "",
    "deviceConfiguration": [],
    "deviceRules": {
      "firmwareUpgrade": "inherit",
      "rcOnly": "inherit",
      "rrm": "inherit"
    },
    "devices": [],
    "id": "2ab42b81-093b-4390-bedd-bca0c0d17d46",
    "locations": [],
    "managementPolicies": [],
    "managementPolicy": "",
    "managementRoles": [],
    "maps": [],
    "modified": 1674643776,
    "name": "Delte LAter",
    "notes": [],
    "parent": "0000-0000-0000",
    "sourceIP": [],
    "tags": [],
    "variables": [],
    "venues": [
      "c470dcb8-992d-4e5c-8c0d-4998946fdea7"
    ]
  },
  {
    "children": [],
    "configurations": [],
    "contacts": [],
    "created": 1674803505,
    "description": "",
    "deviceConfiguration": [],
    "deviceRules": {
      "firmwareUpgrade": "inherit",
      "rcOnly": "inherit",
      "rrm": "inherit"
    },
    "devices": [],
    "id": "109f9b5e-f3cb-484a-ab1e-5aa5a0295dd2",
    "locations": [],
    "managementPolicies": [],
    "managementPolicy": "",
    "managementRoles": [],
    "maps": [],
    "modified": 1674803505,
    "name": "Bulk Import",
    "notes": [],
    "parent": "0000-0000-0000",
    "sourceIP": [],
    "tags": [],
    "variables": [],
    "venues": [
      "01f30faf-7977-4b55-a21e-4304f001d327"
    ]
  },
  {
    "children": [],
    "configurations": [],
    "contacts": [],
    "created": 1674819398,
    "description": "",
    "deviceConfiguration": [],
    "deviceRules": {
      "firmwareUpgrade": "inherit",
      "rcOnly": "inherit",
      "rrm": "inherit"
    },
    "devices": [],
    "id": "1f89d3e7-87ad-478d-ab95-0a066cb850e3",
    "locations": [],
    "managementPolicies": [],
    "managementPolicy": "",
    "managementRoles": [],
    "maps": [],
    "modified": 1674819398,
    "name": "NEWORG23",
    "notes": [],
    "parent": "0000-0000-0000",
    "sourceIP": [],
    "tags": [],
    "variables": [],
    "venues": [
      "f55e7236-d717-477b-904b-0f6a53ded9a7"
    ]
  },
  {
    "children": [],
    "configurations": [],
    "contacts": [],
    "created": 1673000099,
    "description": "",
    "deviceConfiguration": [],
    "deviceRules": {
      "firmwareUpgrade": "inherit",
      "rcOnly": "inherit",
      "rrm": "inherit"
    },
    "devices": [],
    "id": "3e76e156-d8e3-4544-b10d-5e65ba0db375",
    "locations": [],
    "managementPolicies": [],
    "managementPolicy": "",
    "managementRoles": [],
    "maps": [],
    "modified": 1673000099,
    "name": "SWUpgradeTest",
    "notes": [],
    "parent": "0000-0000-0000",
    "sourceIP": [],
    "tags": [],
    "variables": [],
    "venues": [
      "fcf55a29-f93c-452d-a675-c5c4b436545e"
    ]
  }
]